{
  "playerOpt": {
    "startPosition": { "x": 0, "y": 0, "z": 5 }
  },
  "orbitControlsOpt": {
    "enabled": true,
    "rotateSpeed": 0.1,
    "startPosition": { "x": 40, "y": 40, "z": 40 },
    "target": { "x": 0, "y": 0, "z": 0 },
    "enableDamping": true
  },
  "gripOpt": {
    "mainHand": "right"
  },
  "pistolGripOpt": {
    "visible": true,
    "baseGripOpt": {
      "visible": false,
      "scale": 1,
      "position": { "x": 0, "y": 0.2, "z": -0.2 },
      "rotation": { "x": -0.5, "y": 0, "z": 0 }
    },
    "pistol": {
      "scale": 1,
      "position": { "x": 0, "y": 0, "z": 0 },
      "rotation": { "x": 2.09, "y": 0, "z": 3.14 }
    },
    "rayEnabled": 1
  },
  "worldPhysicsOpt": {
    "gravity": {
      "x": 0,
      "y": -9.8,
      "z": 0
    },
    "ccdIterations": 1,
    "timeStep": 0.016,
    "allowed_linear_error": 0.0001
  },
  "commonDebugOpt": {
    "cameraDebug": true,
    "physicsDebug": false,
    "perfDebug": true,
    "timeScale": 1
  }
}
